odoo8_addon_document_page_approval-8.0.1.0.0.99.dev23-py2.7-nspkg.pth
odoo8_addon_document_page_approval-8.0.1.0.0.99.dev23.dist-info/METADATA
odoo8_addon_document_page_approval-8.0.1.0.0.99.dev23.dist-info/RECORD
odoo8_addon_document_page_approval-8.0.1.0.0.99.dev23.dist-info/WHEEL
odoo8_addon_document_page_approval-8.0.1.0.0.99.dev23.dist-info/namespace_packages.txt
odoo8_addon_document_page_approval-8.0.1.0.0.99.dev23.dist-info/top_level.txt
odoo_addons/document_page_approval/README.rst
odoo_addons/document_page_approval/__init__.py
odoo_addons/document_page_approval/__openerp__.py
odoo_addons/document_page_approval/document_page_approval.py
odoo_addons/document_page_approval/document_page_view.xml
odoo_addons/document_page_approval/document_page_wkfl.xml
odoo_addons/document_page_approval/data/email_template.xml
odoo_addons/document_page_approval/i18n/ar.po
odoo_addons/document_page_approval/i18n/bs.po
odoo_addons/document_page_approval/i18n/ca.po
odoo_addons/document_page_approval/i18n/ca_ES.po
odoo_addons/document_page_approval/i18n/cs.po
odoo_addons/document_page_approval/i18n/da.po
odoo_addons/document_page_approval/i18n/de.po
odoo_addons/document_page_approval/i18n/el_GR.po
odoo_addons/document_page_approval/i18n/en_GB.po
odoo_addons/document_page_approval/i18n/es.po
odoo_addons/document_page_approval/i18n/es_AR.po
odoo_addons/document_page_approval/i18n/es_CR.po
odoo_addons/document_page_approval/i18n/es_EC.po
odoo_addons/document_page_approval/i18n/es_ES.po
odoo_addons/document_page_approval/i18n/es_MX.po
odoo_addons/document_page_approval/i18n/es_VE.po
odoo_addons/document_page_approval/i18n/et.po
odoo_addons/document_page_approval/i18n/fi.po
odoo_addons/document_page_approval/i18n/fr.po
odoo_addons/document_page_approval/i18n/fr_CH.po
odoo_addons/document_page_approval/i18n/gl.po
odoo_addons/document_page_approval/i18n/hr.po
odoo_addons/document_page_approval/i18n/hr_HR.po
odoo_addons/document_page_approval/i18n/hu.po
odoo_addons/document_page_approval/i18n/id.po
odoo_addons/document_page_approval/i18n/it.po
odoo_addons/document_page_approval/i18n/ja.po
odoo_addons/document_page_approval/i18n/lt.po
odoo_addons/document_page_approval/i18n/lv.po
odoo_addons/document_page_approval/i18n/mk.po
odoo_addons/document_page_approval/i18n/mn.po
odoo_addons/document_page_approval/i18n/nb.po
